.DS_Store
project/__init__.py
project/mail.py
project/plugin.py
project/user_provision.py
project/plugins/__init__.py
user_provision_tool-1.48.dist-info/DESCRIPTION.rst
user_provision_tool-1.48.dist-info/METADATA
user_provision_tool-1.48.dist-info/RECORD
user_provision_tool-1.48.dist-info/WHEEL
user_provision_tool-1.48.dist-info/entry_points.txt
user_provision_tool-1.48.dist-info/metadata.json
user_provision_tool-1.48.dist-info/top_level.txt
